cvtorchvision/__init__.py
cvtorchvision/cvtransforms/__init__.py
cvtorchvision/cvtransforms/cvfunctional.py
cvtorchvision/cvtransforms/cvtransforms.py
opencv_torchvision_transforms_yuzhiyang-0.0.1.dist-info/LICENSE
opencv_torchvision_transforms_yuzhiyang-0.0.1.dist-info/METADATA
opencv_torchvision_transforms_yuzhiyang-0.0.1.dist-info/WHEEL
opencv_torchvision_transforms_yuzhiyang-0.0.1.dist-info/top_level.txt
opencv_torchvision_transforms_yuzhiyang-0.0.1.dist-info/RECORD
