Metadata-Version: 2.1
Name: opencv-torchvision-transforms-yuzhiyang
Version: 0.0.1
Summary: an opencv based rewriting of the "transforms" in torchvision package
Home-page: https://github.com/YU-Zhiyang/opencv_transforms_torchvision
Author: Yu Zhiyang
Author-email: yuzhiyang@hit.edu.cn
License: UNKNOWN
Platform: UNKNOWN
Classifier: Programming Language :: Python :: 3
Classifier: License :: OSI Approved :: MIT License
Classifier: Operating System :: OS Independent
Requires-Dist: numpy (>=1.10)
Requires-Dist: torchvision (>=0.2.1)
Requires-Dist: opencv-contrib-python (>=3.4.2)
